ppi_network_annotation/__init__.py
ppi_network_annotation/constants.py
ppi_network_annotation/parsers.py
ppi_network_annotation/pipeline.py
ppi_network_annotation/model/__init__.py
ppi_network_annotation/model/attribute_network.py
ppi_network_annotation/model/filtered_network.py
ppi_network_annotation/model/gene.py
ppi_network_annotation/model/labeled_network.py
ppi_network_annotation/model/neighborhood_network.py
ppi_network_annotation/model/network.py
ppi_network_annotation-0.0.3.dist-info/LICENSE
ppi_network_annotation-0.0.3.dist-info/METADATA
ppi_network_annotation-0.0.3.dist-info/WHEEL
ppi_network_annotation-0.0.3.dist-info/top_level.txt
ppi_network_annotation-0.0.3.dist-info/RECORD
