Metadata-Version: 2.1
Name: ppi-network-annotation
Version: 0.0.3
Summary: Library for annotating a protein protein interaction network with differential 
Home-page: https://github.com/GuiltyTargets/ppi-network-annotation
Author: Özlem Muslu
Author-email: ozlemmuslu@gmail.com
Maintainer: Özlem Muslu
Maintainer-email: ozlemmuslu@gmail.com
License: MIT License
Keywords: Protein-Protein Interaction Network,Networks Biology,Annotated Protein-Protein Interaction Network,Differential Gene Expression
Platform: UNKNOWN
Classifier: Development Status :: 4 - Beta
Classifier: Environment :: Console
Classifier: Intended Audience :: Developers
Classifier: Intended Audience :: Science/Research
Classifier: License :: OSI Approved :: MIT License
Classifier: Operating System :: OS Independent
Classifier: Programming Language :: Python
Classifier: Programming Language :: Python :: 3.6
Classifier: Programming Language :: Python :: 3.7
Classifier: Topic :: Scientific/Engineering :: Bio-Informatics
Requires-Dist: numpy
Requires-Dist: xlrd
Requires-Dist: openpyxl
Requires-Dist: python-igraph
Requires-Dist: click
Requires-Dist: dataclasses-json
Requires-Dist: pandas
